antibody_test_01-69.data/scripts/i_love_sam
antibody_test_01-69.dist-info/METADATA
antibody_test_01-69.dist-info/RECORD
antibody_test_01-69.dist-info/WHEEL
antibody_test_01-69.dist-info/top_level.txt
bin/__init__.py
i_love_sam/__init__.py
i_love_sam/i_love.py
