Metadata-Version: 2.1
Name: antibody-test-01
Version: 69
Summary: I love sam
Home-page: UNKNOWN
Author: nilloc
License: MIT License
Platform: UNKNOWN
Classifier: Programming Language :: Python :: 3
Classifier: License :: OSI Approved :: MIT License
Classifier: Operating System :: OS Independent
